<Properties StartupConfiguration="{CCB89B86-F609-4A6C-AE51-340A95AB9841}|Default">
  <MonoDevelop.Ide.Workbench ActiveDocument="Program.cs">
    <Files>
      <File FileName="Program.cs" Line="9" Column="13" />
    </Files>
  </MonoDevelop.Ide.Workbench>
  <MonoDevelop.Ide.Workspace ActiveConfiguration="Debug" />
  <MonoDevelop.Ide.DebuggingService.Breakpoints>
    <BreakpointStore />
  </MonoDevelop.Ide.DebuggingService.Breakpoints>
  <MonoDevelop.Ide.DebuggingService.PinnedWatches />
  <MonoDevelop.Ide.ItemProperties.MoreMath PreferredExecutionTarget="MonoDevelop.Default" FirstBuild="True" />
  <MultiItemStartupConfigurations />
</Properties>